braze/__init__.py
braze/client.py
tests/braze/__init__.py
tests/braze/test_client.py
braze_client_p311-0.0.5.dist-info/LICENSE
braze_client_p311-0.0.5.dist-info/METADATA
braze_client_p311-0.0.5.dist-info/WHEEL
braze_client_p311-0.0.5.dist-info/top_level.txt
braze_client_p311-0.0.5.dist-info/RECORD
