Metadata-Version: 2.1
Name: braze-client-p311
Version: 0.0.5
Summary: Braze Python Client
Home-page: https://github.com/kpeutcr8/braze-client
Author-email: kpeutcr8@yandex.ru
License: UNKNOWN
Keywords: Appboy,Braze
Platform: UNKNOWN
Classifier: Programming Language :: Python
Classifier: Programming Language :: Python :: 2.7
Classifier: Programming Language :: Python :: 3.6
Classifier: Programming Language :: Python :: 3.7
Classifier: Programming Language :: Python :: 3.8
Classifier: Programming Language :: Python :: 3.9
Classifier: Programming Language :: Python :: 3.10
Classifier: Programming Language :: Python :: 3.11
Requires-Python: >=2.7, !=3.0.*, !=3.1.*, !=3.2.*, !=3.3.*, !=3.4.*, !=3.5.*
Requires-Dist: requests (<3.0.0,>=2.21.0)
Requires-Dist: tenacity (==8.2.3)
Provides-Extra: dev
Requires-Dist: tox ; extra == 'dev'
